ishaan/__init__.py
ishaan/tree.py
ishaan-0.1.0.dist-info/WHEEL
ishaan-0.1.0.dist-info/METADATA
ishaan-0.1.0.dist-info/RECORD
