Metadata-Version: 2.1
Name: ishaan
Version: 0.1.0
Summary: 
Author: Ayush Shanker
Author-email: ayushshanker@outlook.in
Requires-Python: >=3.8,<4.0
Classifier: Programming Language :: Python :: 3
Classifier: Programming Language :: Python :: 3.8
Requires-Dist: binarytree (>=5.1.0,<6.0.0)
